README.md
setup.py
prysm/__init__.py
prysm/agemodels/__init__.py
prysm/agemodels/banded.py
prysm/agemodels/tiepoint.py
prysm/api/__init__.py
prysm/api/coral.py
prysm/api/icecore.py
prysm/api/lake.py
prysm/api/speleo.py
prysm/api/tree.py
prysm/aux_functions/__init__.py
prysm/aux_functions/analytical_err_simple.py
prysm/aux_functions/analytical_error.py
prysm/aux_functions/butter_lowpass_filter.py
prysm/cellulose/__init__.py
prysm/cellulose/sensor.py
prysm/coral/__init__.py
prysm/coral/sensor.py
prysm/icecore/__init__.py
prysm/icecore/archive.py
prysm/icecore/sensor.py
prysm/speleo/__init__.py
prysm/speleo/sensor.py
prysm3.egg-info/PKG-INFO
prysm3.egg-info/SOURCES.txt
prysm3.egg-info/dependency_links.txt
prysm3.egg-info/not-zip-safe
prysm3.egg-info/top_level.txt