Metadata-Version: 2.1
Name: prysm3
Version: 0.2.1
Summary: open-source tools for PRoxY System Modeling
Home-page: https://github.com/fzhu2e/PRYSM
Author: Sylvia Dee, Amir Allam, and Feng Zhu
License: MIT license
Keywords: prysm3
Platform: UNKNOWN
Classifier: License :: OSI Approved :: MIT License
Classifier: Natural Language :: English
Classifier: Programming Language :: Python :: 3
Classifier: Programming Language :: Python :: 3.6
